Social_Media_Sentiment_Analysis/NLP_Classification.py
Social_Media_Sentiment_Analysis/Social_Media.py
Social_Media_Sentiment_Analysis/__init__.py
Social_Media_Sentiment_Analysis-0.1.3.dist-info/LICENSE
Social_Media_Sentiment_Analysis-0.1.3.dist-info/METADATA
Social_Media_Sentiment_Analysis-0.1.3.dist-info/WHEEL
Social_Media_Sentiment_Analysis-0.1.3.dist-info/top_level.txt
Social_Media_Sentiment_Analysis-0.1.3.dist-info/RECORD
