Metadata-Version: 2.1
Name: Social-Media-Sentiment-Analysis
Version: 0.1.3
Summary: A Library for webscraping social media platforms (twitter) and using sentiment analysis on them!
Home-page: https://social_media_sentiment_analysis.readthedocs.io/
Author: Raf Muz
Author-email: CyberRaf01@gmail.com
License: MIT
Platform: UNKNOWN
Classifier: Intended Audience :: Developers
Classifier: License :: OSI Approved :: MIT License
Classifier: Programming Language :: Python
Classifier: Programming Language :: Python :: 3
Classifier: Programming Language :: Python :: 3.7
Classifier: Programming Language :: Python :: 3.8
Classifier: Programming Language :: Python :: 3.9
Classifier: Programming Language :: Python :: 3.10
Classifier: Operating System :: OS Independent
Requires-Dist: snscrape
Requires-Dist: flair (>=0.11.1)
Requires-Dist: pandas
